appimagebuilder/__init__.py
appimagebuilder/__main__.py
appimagebuilder/context.py
appimagebuilder/invoker.py
appimagebuilder/orchestrator.py
appimagebuilder/cli/__init__.py
appimagebuilder/cli/argparse.py
appimagebuilder/commands/__init__.py
appimagebuilder/commands/apt_deploy.py
appimagebuilder/commands/command.py
appimagebuilder/commands/create_appimage.py
appimagebuilder/commands/deploy_record.py
appimagebuilder/commands/file_deploy.py
appimagebuilder/commands/pacman_deploy.py
appimagebuilder/commands/run_script.py
appimagebuilder/commands/run_test.py
appimagebuilder/commands/setup_app_info.py
appimagebuilder/commands/setup_runtime.py
appimagebuilder/commands/setup_symlinks.py
appimagebuilder/modules/__init__.py
appimagebuilder/modules/appimage.py
appimagebuilder/modules/analisys/__init__.py
appimagebuilder/modules/analisys/app_runtime_analyser.py
appimagebuilder/modules/analisys/appimage_mount.py
appimagebuilder/modules/analisys/inspector.py
appimagebuilder/modules/deploy/__init__.py
appimagebuilder/modules/deploy/util.py
appimagebuilder/modules/deploy/apt/__init__.py
appimagebuilder/modules/deploy/apt/deploy.py
appimagebuilder/modules/deploy/apt/errors.py
appimagebuilder/modules/deploy/apt/listings.py
appimagebuilder/modules/deploy/apt/package.py
appimagebuilder/modules/deploy/apt/venv.py
appimagebuilder/modules/deploy/files/__init__.py
appimagebuilder/modules/deploy/files/deploy_helper.py
appimagebuilder/modules/deploy/files/dependencies_resolver/__init__.py
appimagebuilder/modules/deploy/files/dependencies_resolver/base_resolver.py
appimagebuilder/modules/deploy/files/dependencies_resolver/elf_resolver.py
appimagebuilder/modules/deploy/files/dependencies_resolver/resolver.py
appimagebuilder/modules/deploy/pacman/__init__.py
appimagebuilder/modules/deploy/pacman/deploy.py
appimagebuilder/modules/deploy/pacman/venv.py
appimagebuilder/modules/generate/__init__.py
appimagebuilder/modules/generate/apt_recipe_generator.py
appimage_builder-1.1.0.dist-info/LICENSE
appimage_builder-1.1.0.dist-info/METADATA
appimage_builder-1.1.0.dist-info/WHEEL
appimage_builder-1.1.0.dist-info/entry_points.txt
appimage_builder-1.1.0.dist-info/top_level.txt
appimage_builder-1.1.0.dist-info/RECORD
