Metadata-Version: 2.1
Name: appimage-builder
Version: 1.1.0
Summary: Recipe based AppImage creation meta-tool
Home-page: https://github.com/AppImageCrafters/appimage-builder
Author: Alexis Lopez Zubieta
Author-email: contact@azubieta.net
License: MIT
Project-URL: Bug Tracker, https://github.com/AppImageCrafters/appimage-builder/issues
Project-URL: Documentation, https://appimage-builder.readthedocs.io
Project-URL: Source Code, https://github.com/AppImageCrafters/appimage-builder
Platform: UNKNOWN
Classifier: Programming Language :: Python :: 3
Classifier: License :: OSI Approved :: MIT License
Requires-Python: >=3.6
License-File: LICENSE
